mplcamera/__init__.py
mplcamera-0.0.2.dist-info/LICENSE.txt
mplcamera-0.0.2.dist-info/METADATA
mplcamera-0.0.2.dist-info/WHEEL
mplcamera-0.0.2.dist-info/top_level.txt
mplcamera-0.0.2.dist-info/RECORD
