Metadata-Version: 2.1
Name: mplcamera
Version: 0.0.2
Summary: Camera Class to make snapshots of a figure and save a gif from stored images
Home-page: https://github.com/znstrider/mplcamera
Author: znstrider
Author-email: mindfulstrider@gmail.com
License: UNKNOWN
Platform: UNKNOWN
Classifier: Programming Language :: Python :: 3
Classifier: License :: OSI Approved :: MIT License
Classifier: Operating System :: OS Independent
Classifier: Framework :: Matplotlib
Classifier: Topic :: Scientific/Engineering :: Visualization
Requires-Python: >=3.6
